end2/__init__.py
end2/arg_parser.py
end2/constants.py
end2/discovery.py
end2/exceptions.py
end2/fixtures.py
end2/resource_profile.py
end2/runner.py
end2-1.3.dist-info/LICENSE.txt
end2-1.3.dist-info/METADATA
end2-1.3.dist-info/WHEEL
end2-1.3.dist-info/top_level.txt
end2-1.3.dist-info/RECORD
