Metadata-Version: 2.1
Name: end2
Version: 1.3
Summary: A Minimal E2E Test Automation Framework
Home-page: https://github.com/jonwesneski/end2
Author: Jon Wesneski
Author-email: jonwes2@gmail.com
License: MIT
Keywords: end-2-end,end2end,end-to-end,endtoend,e2e,end2,testing,qa,automation
Classifier: Development Status :: 3 - Alpha
Classifier: Topic :: Software Development :: Quality Assurance
Classifier: Topic :: Software Development :: Testing
Classifier: Topic :: Software Development :: Testing :: Acceptance
Classifier: License :: OSI Approved :: MIT License
Classifier: Programming Language :: Python :: 3.8
Classifier: Programming Language :: Python :: 3.9
Classifier: Programming Language :: Python :: 3.10
License-File: LICENSE.txt
